summarize_dataframe/__init__.py
summarize_dataframe/summarize_df.py
summarize_dataframe-0.3.0.dist-info/WHEEL
summarize_dataframe-0.3.0.dist-info/METADATA
summarize_dataframe-0.3.0.dist-info/RECORD
