Metadata-Version: 2.1
Name: summarize-dataframe
Version: 0.3.0
Summary: A package to provide summary data about pandas DataFrame
Home-page: https://github.com/fbraza/summarize_dataframe
License: MIT
Keywords: pandas,dataframe
Author: fbraza
Author-email: fbraza@tutanota.com
Requires-Python: >=3.7.1,<4.0.0
Classifier: License :: OSI Approved :: MIT License
Classifier: Programming Language :: Python :: 3
Classifier: Programming Language :: Python :: 3.8
Classifier: Programming Language :: Python :: 3.9
Project-URL: Repository, https://github.com/fbraza/summarize_dataframe
